{
  "width": 14,
  "height": 8,
  "tiles": [
      { "x": 0, "y": 3, "type": "start"},
      { "x": 3, "y": 1, "type": "obstacle"}, 
      { "x": 3, "y": 2, "type": "obstacle"}, 
      { "x": 3, "y": 3, "type": "obstacle"}, 
      { "x": 3, "y": 4, "type": "obstacle"}, 
      { "x": 3, "y": 5, "type": "obstacle"},
      { "x": 4, "y": 1, "type": "obstacle"}, 
      { "x": 4, "y": 2, "type": "obstacle"},
      { "x": 4, "y": 3, "type": "obstacle"}, 
      { "x": 4, "y": 4, "type": "obstacle"}, 
      { "x": 4, "y": 5, "type": "obstacle"}, 
      { "x": 7, "y": 3, "type": "obstacle"}, 
      { "x": 8, "y": 3, "type": "obstacle"}, 
      { "x": 9, "y": 3, "type": "obstacle"}, 
      { "x": 10, "y": 3, "type": "obstacle"}, 
      { "x": 12, "y": 2, "type": "obstacle"}, 
      { "x": 12, "y": 3, "type": "goal"}, 
      { "x": 12, "y": 4, "type": "obstacle"}
  ],
  "player": {"x": 0, "y": 3},
  "objects": [
      {"type": "skeleton", "x": 5, "y": 0, "path": "LRRL"},
      {"type": "skeleton", "x": 5, "y": 6, "path": "LRRL"},
      {"type": "slime", "x": 7, "y": 0, "path": "URDL"},
      {"type": "slime", "x": 7, "y": 6, "path": "LURD"},
      {"type": "slime", "x": 9, "y": 2, "path": "RDLU"},
      {"type": "slime", "x": 9, "y": 4, "path": "RULD"},
      {"type": "slime", "x": 11, "y": 3, "path": "UDDU"},
      {"type": "platform", "x": 3, "y": 3, "path": "UNUNRNDNDNDNDNLNUNUN"}
  ],
  "ticker": "MMMD"
}
 
